filesdump/cam_capture.v
// ============================================================
// cam_capture.v  –  OV7670 parallel data capture
//
// The OV7670 in RGB565 mode sends each pixel as TWO bytes:
//   Byte 1 (first PCLK):  [R4:R0 G5:G3]  – upper byte
//   Byte 2 (second PCLK): [G2:G0 B4:B0]  – lower byte
//
// We down-convert to 12-bit RGB444 for BRAM storage:
//   R[3:0] = byte1[7:4]
//   G[3:0] = {byte1[2:0], byte2[7]}  → take top 4 of 6 green bits
//   B[3:0] = byte2[4:1]
//
// Frame size written: 320 x 240 = 76,800 pixels
// ============================================================
module cam_capture (
    input  wire        pclk,
    input  wire        href,
    input  wire        vsync,
    input  wire [7:0]  din,

    output reg  [16:0] wr_addr,
    output reg  [11:0] wr_data,
    output reg         wr_en
);

    reg        byte_sel = 0;     // 0=first byte, 1=second byte
    reg [7:0]  byte1    = 0;
    reg [8:0]  col      = 0;     // 0..319
    reg [7:0]  row      = 0;     // 0..239
    reg        vsync_prev = 0;

    always @(negedge pclk) begin
        wr_en      <= 0;
        vsync_prev <= vsync;

        // Rising edge of VSYNC → reset frame position
        if (vsync && !vsync_prev) begin
            col      <= 0;
            row      <= 0;
            byte_sel <= 0;
        end

        if (href) begin
            if (!byte_sel) begin
                // First byte of pixel
                byte1    <= din;
                byte_sel <= 1;
            end else begin
                // Second byte of pixel → assemble RGB444 and write
                byte_sel <= 0;

                // Only store pixels within 320x240 window
                if (col < 320 && row < 240) begin
                    wr_data <= { byte1[7:4],          // R[3:0]
                                 byte1[2:0], din[7],  // G[3:0]
                                 din[4:1]             // B[3:0]
                               };
                    wr_addr <= row * 320 + col;
                    wr_en   <= 1;
                end

                // Advance column
                if (col < 319) begin
                    col <= col + 1;
                end
            end
        end else begin
            // HREF just went low → end of line
            if (byte_sel) byte_sel <= 0;  // reset byte alignment
            if (col != 0 || byte_sel) begin
                // Only count row when we actually had pixels
                if (col > 0) begin
                    row <= (row < 239) ? row + 1 : row;
                end
                col <= 0;
            end
        end
    end

endmodule

filesdump/tb_cam_capture.v
// ============================================================
// tb_cam_capture.v  –  Testbench for cam_capture module
// Simulates OV7670 RGB565 output for a 4x3 pixel mini-frame
// and checks that pixel data is correctly assembled and stored
// ============================================================
`timescale 1ns/1ps

module tb_cam_capture;

    reg        pclk   = 0;
    reg        href   = 0;
    reg        vsync  = 0;
    reg [7:0]  din    = 0;

    wire [16:0] wr_addr;
    wire [11:0] wr_data;
    wire         wr_en;

    // DUT
    cam_capture dut (
        .pclk    (pclk),
        .href    (href),
        .vsync   (vsync),
        .din     (din),
        .wr_addr (wr_addr),
        .wr_data (wr_data),
        .wr_en   (wr_en)
    );

    // 24 MHz PCLK  (period ≈ 41.67 ns)
    always #21 pclk = ~pclk;

    // Task: send one RGB565 pixel
    // r,g,b are 5,6,5 bit values
    task send_pixel;
        input [4:0] r;
        input [5:0] g;
        input [4:0] b;
        reg [15:0] pixel;
        begin
            pixel = {r, g, b};
            // Byte 1: [R4:R0 G5:G3]
            din = pixel[15:8];
            @(posedge pclk); #1;
            // Byte 2: [G2:G0 B4:B0]
            din = pixel[7:0];
            @(posedge pclk); #1;
        end
    endtask

    // Task: send one row of pixels
    task send_row;
        input integer n_pix;
        input [4:0] r; input [5:0] g; input [4:0] b;
        integer j;
        begin
            href = 1;
            for (j = 0; j < n_pix; j = j + 1)
                send_pixel(r, g, b);
            href = 0;
            @(posedge pclk); @(posedge pclk); // gap between rows
        end
    endtask

    integer pixel_cnt = 0;
    always @(posedge pclk) begin
        if (wr_en) begin
            pixel_cnt <= pixel_cnt + 1;
            $display("Pixel %0d  addr=%0d  RGB444=%03h  at %0t",
                     pixel_cnt, wr_addr, wr_data, $time);
        end
    end

    initial begin
        $dumpfile("tb_cam_capture.vcd");
        $dumpvars(0, tb_cam_capture);

        // ---- VSYNC pulse (frame start) ----
        vsync = 1;
        repeat(4) @(posedge pclk);
        vsync = 0;
        repeat(2) @(posedge pclk);

        // ---- Row 0:  RED pixels  (R=31, G=0, B=0 in RGB565) ----
        send_row(4, 5'd31, 6'd0, 5'd0);

        // ---- Row 1:  GREEN pixels (R=0, G=63, B=0) ----
        send_row(4, 5'd0, 6'd63, 5'd0);

        // ---- Row 2:  BLUE pixels  (R=0, G=0, B=31) ----
        send_row(4, 5'd0, 6'd0, 5'd31);

        repeat(10) @(posedge pclk);

        // Check total pixel count
        if (pixel_cnt == 12)
            $display("PASS: captured %0d pixels (expected 12)", pixel_cnt);
        else
            $display("FAIL: captured %0d pixels (expected 12)", pixel_cnt);

        $finish;
    end

endmodule

filesdump/tb_cam_capture.vcd
$date
	Wed Apr 22 14:32:39 2026
$end
$version
	Icarus Verilog
$end
$timescale
	1ps
$end
$scope module tb_cam_capture $end
$var wire 1 ! wr_en $end
$var wire 12 " wr_data [11:0] $end
$var wire 17 # wr_addr [16:0] $end
$var reg 8 $ din [7:0] $end
$var reg 1 % href $end
$var reg 1 & pclk $end
$var reg 1 ' vsync $end
$var integer 32 ( pixel_cnt [31:0] $end
$scope module dut $end
$var wire 8 ) din [7:0] $end
$var wire 1 % href $end
$var wire 1 & pclk $end
$var wire 1 ' vsync $end
$var reg 8 * byte1 [7:0] $end
$var reg 1 + byte_sel $end
$var reg 9 , col [8:0] $end
$var reg 8 - row [7:0] $end
$var reg 1 . vsync_prev $end
$var reg 17 / wr_addr [16:0] $end
$var reg 12 0 wr_data [11:0] $end
$var reg 1 ! wr_en $end
$upscope $end
$scope task send_pixel $end
$var reg 5 1 b [4:0] $end
$var reg 6 2 g [5:0] $end
$var reg 16 3 pixel [15:0] $end
$var reg 5 4 r [4:0] $end
$upscope $end
$scope task send_row $end
$var reg 5 5 b [4:0] $end
$var reg 6 6 g [5:0] $end
$var reg 5 7 r [4:0] $end
$var integer 32 8 j [31:0] $end
$var integer 32 9 n_pix [31:0] $end
$upscope $end
$upscope $end
$enddefinitions $end
$comment Show the parameter values. $end
$dumpall
$end
#0
$dumpvars
bx 9
bx 8
bx 7
bx 6
bx 5
bx 4
bx 3
bx 2
bx 1
bx 0
bx /
0.
b0 -
b0 ,
0+
b0 *
b0 )
b0 (
1'
0&
0%
b0 $
bx #
bx "
x!
$end
#21000
1.
0!
1&
#42000
0&
#63000
1&
#84000
0&
#105000
1&
#126000
0&
#147000
0'
1&
#168000
0&
#189000
0.
1&
#210000
0&
#231000
b11111000 $
b11111000 )
b1111100000000000 3
b0 1
b0 2
b11111 4
b0 8
1%
b0 5
b0 6
b11111 7
b100 9
1&
#252000
0&
#273000
1+
b11111000 *
1&
#274000
b0 $
b0 )
#294000
0&
#315000
b1 ,
1!
b0 #
b0 /
b111100000000 "
b111100000000 0
0+
1&
#316000
b11111000 $
b11111000 )
b1 8
#336000
0&
#357000
1+
0!
b1 (
1&
#358000
b0 $
b0 )
#378000
0&
#399000
b10 ,
1!
b1 #
b1 /
0+
1&
#400000
b11111000 $
b11111000 )
b10 8
#420000
0&
#441000
1+
0!
b10 (
1&
#442000
b0 $
b0 )
#462000
0&
#483000
b11 ,
1!
b10 #
b10 /
0+
1&
#484000
b11111000 $
b11111000 )
b11 8
#504000
0&
#525000
1+
0!
b11 (
1&
#526000
b0 $
b0 )
#546000
0&
#567000
b100 ,
1!
b11 #
b11 /
0+
1&
#568000
0%
b100 8
#588000
0&
#609000
b0 ,
b1 -
0!
b100 (
1&
#630000
0&
#651000
b111 $
b111 )
b11111100000 3
b111111 2
b0 4
b0 8
1%
b111111 6
b0 7
1&
#672000
0&
#693000
1+
b111 *
1&
#694000
b11100000 $
b11100000 )
#714000
0&
#735000
b1 ,
1!
b101000000 #
b101000000 /
b11110000 "
b11110000 0
0+
1&
#736000
b111 $
b111 )
b1 8
#756000
0&
#777000
1+
0!
b101 (
1&
#778000
b11100000 $
b11100000 )
#798000
0&
#819000
b10 ,
1!
b101000001 #
b101000001 /
0+
1&
#820000
b111 $
b111 )
b10 8
#840000
0&
#861000
1+
0!
b110 (
1&
#862000
b11100000 $
b11100000 )
#882000
0&
#903000
b11 ,
1!
b101000010 #
b101000010 /
0+
1&
#904000
b111 $
b111 )
b11 8
#924000
0&
#945000
1+
0!
b111 (
1&
#946000
b11100000 $
b11100000 )
#966000
0&
#987000
b100 ,
1!
b101000011 #
b101000011 /
0+
1&
#988000
0%
b100 8
#1008000
0&
#1029000
b0 ,
b10 -
0!
b1000 (
1&
#1050000
0&
#1071000
b0 $
b0 )
b11111 3
b11111 1
b0 2
b0 8
1%
b11111 5
b0 6
1&
#1092000
0&
#1113000
1+
b0 *
1&
#1114000
b11111 $
b11111 )
#1134000
0&
#1155000
b1 ,
1!
b1010000000 #
b1010000000 /
b1111 "
b1111 0
0+
1&
#1156000
b0 $
b0 )
b1 8
#1176000
0&
#1197000
1+
0!
b1001 (
1&
#1198000
b11111 $
b11111 )
#1218000
0&
#1239000
b10 ,
1!
b1010000001 #
b1010000001 /
0+
1&
#1240000
b0 $
b0 )
b10 8
#1260000
0&
#1281000
1+
0!
b1010 (
1&
#1282000
b11111 $
b11111 )
#1302000
0&
#1323000
b11 ,
1!
b1010000010 #
b1010000010 /
0+
1&
#1324000
b0 $
b0 )
b11 8
#1344000
0&
#1365000
1+
0!
b1011 (
1&
#1366000
b11111 $
b11111 )
#1386000
0&
#1407000
b100 ,
1!
b1010000011 #
b1010000011 /
0+
1&
#1408000
0%
b100 8
#1428000
0&
#1449000
b0 ,
b11 -
0!
b1100 (
1&
